setup.py
pairwise/__init__.py
pairwise.egg-info/PKG-INFO
pairwise.egg-info/SOURCES.txt
pairwise.egg-info/dependency_links.txt
pairwise.egg-info/not-zip-safe
pairwise.egg-info/top_level.txt