Metadata-Version: 1.0
Name: pairwise
Version: 0.1
Summary: Tools for statistical analysis of pairwise survey data.
Home-page: https://github.com/davefol/pairwise
Author: Dave Fol
Author-email: dof5@cornell.edu
License: GNU
Platform: UNKNOWN
